gps_anomaly/__init__.py
gps_anomaly/detect_functions.py
gps_anomaly/detector.py
gps_anomaly/one_sequence.py
gps_anomaly/version.py
gps_anomaly/config/distance.py
gps_anomaly/config/heading.py
gps_anomaly/config/info_anomalies.py
gps_anomaly_detector-0.2.2.dist-info/METADATA
gps_anomaly_detector-0.2.2.dist-info/WHEEL
gps_anomaly_detector-0.2.2.dist-info/top_level.txt
gps_anomaly_detector-0.2.2.dist-info/RECORD
