Metadata-Version: 2.1
Name: gps-anomaly-detector
Version: 0.2.2
Summary: Gps Anomaly Detector of Mapilio
Home-page: https://github.com/mapilio/gps_anomaly_detection
Author: Mapilio
License: MIT License
Requires-Python: >=3.7
Requires-Dist: poetry-core >=1.0.0
